specfact_cli/__init__.py
specfact_cli/__main__.py
specfact_cli/cli.py
specfact_cli/runtime.py
specfact_cli/telemetry.py
specfact_cli/adapters/__init__.py
specfact_cli/adapters/ado.py
specfact_cli/adapters/backlog_base.py
specfact_cli/adapters/base.py
specfact_cli/adapters/github.py
specfact_cli/adapters/openspec.py
specfact_cli/adapters/openspec_parser.py
specfact_cli/adapters/registry.py
specfact_cli/adapters/speckit.py
specfact_cli/agents/__init__.py
specfact_cli/agents/analyze_agent.py
specfact_cli/agents/base.py
specfact_cli/agents/plan_agent.py
specfact_cli/agents/registry.py
specfact_cli/agents/sync_agent.py
specfact_cli/analyzers/__init__.py
specfact_cli/analyzers/ambiguity_scanner.py
specfact_cli/analyzers/code_analyzer.py
specfact_cli/analyzers/constitution_evidence_extractor.py
specfact_cli/analyzers/contract_extractor.py
specfact_cli/analyzers/control_flow_analyzer.py
specfact_cli/analyzers/graph_analyzer.py
specfact_cli/analyzers/relationship_mapper.py
specfact_cli/analyzers/requirement_extractor.py
specfact_cli/analyzers/test_pattern_extractor.py
specfact_cli/backlog/__init__.py
specfact_cli/backlog/ai_refiner.py
specfact_cli/backlog/converter.py
specfact_cli/backlog/filters.py
specfact_cli/backlog/format_detector.py
specfact_cli/backlog/template_detector.py
specfact_cli/backlog/adapters/__init__.py
specfact_cli/backlog/adapters/base.py
specfact_cli/backlog/adapters/local_yaml_adapter.py
specfact_cli/backlog/formats/__init__.py
specfact_cli/backlog/formats/base.py
specfact_cli/backlog/formats/markdown_format.py
specfact_cli/backlog/formats/structured_format.py
specfact_cli/backlog/mappers/__init__.py
specfact_cli/backlog/mappers/ado_mapper.py
specfact_cli/backlog/mappers/base.py
specfact_cli/backlog/mappers/github_mapper.py
specfact_cli/backlog/mappers/template_config.py
specfact_cli/commands/__init__.py
specfact_cli/commands/analyze.py
specfact_cli/commands/auth.py
specfact_cli/commands/backlog_commands.py
specfact_cli/commands/contract_cmd.py
specfact_cli-0.26.15.dist-info/METADATA
specfact_cli-0.26.15.dist-info/WHEEL
specfact_cli-0.26.15.dist-info/entry_points.txt
specfact_cli-0.26.15.dist-info/licenses/LICENSE.md
specfact_cli-0.26.15.dist-info/RECORD
