Metadata-Version: 2.4
Name: specfact-cli
Version: 0.26.15
Summary: Brownfield-first CLI: Reverse engineer legacy Python → specs → enforced contracts. Automate legacy code documentation and prevent modernization regressions.
Project-URL: Homepage, https://github.com/nold-ai/specfact-cli
Project-URL: Repository, https://github.com/nold-ai/specfact-cli.git
Project-URL: Documentation, https://github.com/nold-ai/specfact-cli#readme
Project-URL: Issues, https://github.com/nold-ai/specfact-cli/issues
Project-URL: Trademarks, https://github.com/nold-ai/specfact-cli/blob/main/TRADEMARKS.md
Author-email: "NOLD AI (Owner: Dominikus Nold)" <hello@noldai.com>
License:                                  Apache License
License-File: LICENSE.md
Keywords: async,beartype,brownfield,cli,code-documentation,code-to-spec,contract-driven-development,contracts,crosshair,icontract,legacy-code,modernization,property-based-testing,quality-gates,refactoring,reverse-engineering,spec-first,specfact,state-machine,tdd,technical-debt
Classifier: Development Status :: 4 - Beta
Classifier: Intended Audience :: Developers
Classifier: License :: OSI Approved :: Apache Software License
Classifier: Programming Language :: Python :: 3
Classifier: Programming Language :: Python :: 3.11
Classifier: Programming Language :: Python :: 3.12
Classifier: Programming Language :: Python :: 3.13
Classifier: Topic :: Software Development :: Libraries :: Python Modules
Classifier: Topic :: Software Development :: Quality Assurance
Classifier: Topic :: Software Development :: Testing
Requires-Python: >=3.11
Requires-Dist: azure-identity>=1.17.1
Requires-Dist: beartype>=0.22.4
Requires-Dist: crosshair-tool>=0.0.97
Requires-Dist: gitpython>=3.1.45
Requires-Dist: graphviz>=0.20.1
Requires-Dist: hypothesis>=6.142.4
Requires-Dist: icontract>=2.7.1
Requires-Dist: jinja2>=3.1.6
Requires-Dist: jsonschema>=4.23.0
Requires-Dist: networkx>=3.4.2
Requires-Dist: opentelemetry-exporter-otlp-proto-http>=1.27.0
Requires-Dist: opentelemetry-sdk>=1.27.0
Requires-Dist: pydantic>=2.12.3
Requires-Dist: python-dotenv>=1.2.1
Requires-Dist: pyyaml>=6.0.3
Requires-Dist: questionary>=2.0.1
Requires-Dist: requests>=2.32.3
Requires-Dist: rich<13.6.0,>=13.5.2
Requires-Dist: ruamel-yaml>=0.18.16
Requires-Dist: ruff>=0.14.2
Requires-Dist: typer>=0.20.0
Requires-Dist: typing-extensions>=4.15.0
Requires-Dist: watchdog>=6.0.0
Provides-Extra: dev
Requires-Dist: basedpyright>=1.32.1; extra == 'dev'
Requires-Dist: bearer>=3.1.0; extra == 'dev'
Requires-Dist: beartype>=0.22.4; extra == 'dev'
Requires-Dist: crosshair-tool>=0.0.97; extra == 'dev'
Requires-Dist: graphviz>=0.20.1; extra == 'dev'
Requires-Dist: hypothesis>=6.142.4; extra == 'dev'
Requires-Dist: icontract>=2.7.1; extra == 'dev'
Requires-Dist: isort>=7.0.0; extra == 'dev'
Requires-Dist: pip-tools>=7.5.1; extra == 'dev'
Requires-Dist: pyan3>=1.2.0; extra == 'dev'
Requires-Dist: pylint>=4.0.2; extra == 'dev'
Requires-Dist: pytest-asyncio>=1.2.0; extra == 'dev'
Requires-Dist: pytest-cov>=7.0.0; extra == 'dev'
Requires-Dist: pytest-mock>=3.15.1; extra == 'dev'
Requires-Dist: pytest-xdist>=3.8.0; extra == 'dev'
Requires-Dist: pytest>=8.4.2; extra == 'dev'
Requires-Dist: ruff>=0.14.2; extra == 'dev'
Requires-Dist: semgrep>=1.144.0; extra == 'dev'
Requires-Dist: tomlkit>=0.13.3; extra == 'dev'
Requires-Dist: types-pyyaml>=6.0.12.20250516; extra == 'dev'
Provides-Extra: enhanced-analysis
Requires-Dist: bearer>=3.1.0; extra == 'enhanced-analysis'
Requires-Dist: graphviz>=0.20.1; extra == 'enhanced-analysis'
Requires-Dist: pyan3>=1.2.0; extra == 'enhanced-analysis'
Requires-Dist: syft>=0.9.5; extra == 'enhanced-analysis'
Provides-Extra: scanning
Requires-Dist: semgrep>=1.144.0; extra == 'scanning'
